FPGA/VHDL/other_components/clear_led_logic/clear_led_logic.vhdl


library IEEE;
use IEEE.std_logic_1164.all;
use IEEE.numeric_std.all;


entity clear_led_logic is
	generic (
		G_COUNTER_BITS: integer := 17;
		G_TIMEOUT_COUNTER_BITS: integer := 15

	);
	port (
		clock_clk                   : in  std_logic                     := '0';             --                clock.clk
		reset_reset                 : in  std_logic                     := '0';
		qspi_cs                     : in std_logic    := '0';
		clear_led_pulse             : out std_logic;
		clear_led_prohibit_fire     : out std_logic
    );
end entity clear_led_logic;

architecture rtl of clear_led_logic is

    signal counter :unsigned(G_COUNTER_BITS -1 downto 0);
    signal deadtime_counter :unsigned(G_TIMEOUT_COUNTER_BITS -1 downto 0);

    signal qspi_cs_ff :std_logic_vector(1 downto 0);
    signal qspi_cs_done_ff :std_logic_vector(5 downto 0);
    signal qspi_cs_done :std_logic;


begin
	clear_led_prohibit_fire <= not qspi_cs_done;
	-- generate internal pulse
   p_count: process(all)
	begin
		if reset_reset ='0' then
            counter <= (others=>'0');
		elsif rising_edge(clock_clk) then
            counter <= counter + 1;
		end if;
	end process;
	
	-- double flopping in input signals
	p_in_flooping: process(all)
	begin
		if reset_reset ='0' then
            qspi_cs_ff <= (others=>'0');
		elsif rising_edge(clock_clk) then
            qspi_cs_ff <= qspi_cs_ff(0) & qspi_cs;
		end if;
	end process;

	p_edge_deadtime_counter: process(all)
	begin
		if reset_reset ='0' then
            deadtime_counter <= (others=>'0');
		elsif rising_edge(clock_clk) then
			if qspi_cs_ff(1)='0' and qspi_cs_ff(0)='1' then
				deadtime_counter <= (0=>'1', others=>'0');
			end if;

			if deadtime_counter > 0 then
				deadtime_counter <= deadtime_counter + 1;
			end if;

		end if;
	end process;

	p_logic: process(all)
	begin
		if reset_reset ='0' then
            qspi_cs_done <= '0';
            qspi_cs_done_ff <= (others=>'0');
		elsif rising_edge(clock_clk) then
            if qspi_cs_ff(1)='0' and qspi_cs_ff(0)='1' and deadtime_counter=0 then
				qspi_cs_done_ff <= qspi_cs_done_ff(4 downto 0) & '1';
            end if;

			if qspi_cs_done_ff(5) = '1' then
				qspi_cs_done <= '1';
            end if;
		end if;
	end process;

	p_output: process(all)
	begin
		if reset_reset ='0' then
            clear_led_pulse <= '0';
		elsif rising_edge(clock_clk) then
            if qspi_cs_done='0' and counter=0 then
				clear_led_pulse <= '1';
			else
				clear_led_pulse <= '0';
            end if;
		end if;
	end process;


end architecture;

FPGA/VHDL/other_components/clear_led_logic/clear_led_logic_tb.vhdl


library IEEE;
use IEEE.std_logic_1164.all;
use IEEE.numeric_std.all;

library std;
use std.textio.all;

entity clear_led_logic_tb is
end entity clear_led_logic_tb;

architecture rtl of clear_led_logic_tb is
    component clear_led_logic is
        generic (
		G_COUNTER_BITS : integer := 17;
		G_TIMEOUT_COUNTER_BITS: integer := 15
	);
	port (
		clock_clk                   : in  std_logic                     := '0';             --                clock.clk
		reset_reset                 : in  std_logic                     := '0';
		qspi_cs                     : in std_logic := '0';
		clear_led_pulse             : out std_logic;
		clear_led_prohibit_fire     : out std_logic
        );
    end component;

    signal s_clock                     : std_logic;
    signal s_reset                     : std_logic;
    signal s_qspi_cs                   : std_logic;
    signal s_clear_led_pulse           : std_logic;
    signal s_clear_led_prohibit_fire   : std_logic;

    constant c_cycle_time_12M : time := 83 ns;
    signal enable :boolean:=true;

begin

    dut :clear_led_logic
    generic map (
            G_COUNTER_BITS  => 8,
            G_TIMEOUT_COUNTER_BITS  => 6
        )
    port map(
        clock_clk                  => s_clock,
        reset_reset                => s_reset,
        qspi_cs                    => s_qspi_cs,
        clear_led_pulse            => s_clear_led_pulse,
        clear_led_prohibit_fire    => s_clear_led_prohibit_fire
    );

    s_reset <= transport '0', '1' after 50 ns;

    p_system_clk : process
	begin
		while enable loop
            s_clock <= '0';
            wait for c_cycle_time_12M/2;
            s_clock <= '1';
            wait for c_cycle_time_12M/2;
		end loop;
		wait;  -- don't do it again
	end process p_system_clk;

    p_stim : process
	begin
        s_qspi_cs <= '0';
        
        wait for 100 us;
        s_qspi_cs <= '1';
        wait for 100 us;

        s_qspi_cs <= '0';
        wait for 50 us;
        s_qspi_cs <= '1';
        wait for 500 ns;
        s_qspi_cs <= '0';
        wait for 1 us;
        s_qspi_cs <= '1';
        wait for 20 us;

        s_qspi_cs <= '0';
        wait for 50 us;
        s_qspi_cs <= '1';
        wait for 100 us;

        s_qspi_cs <= '0';
        wait for 50 us;
        s_qspi_cs <= '1';
        wait for 100 us;

        s_qspi_cs <= '0';
        wait for 50 us;
        s_qspi_cs <= '1';
        wait for 100 us;

        s_qspi_cs <= '0';
        wait for 50 us;
        s_qspi_cs <= '1';
        wait for 100 us;

        s_qspi_cs <= '0';
        wait for 50 us;
        s_qspi_cs <= '1';
        wait for 100 us;

        s_qspi_cs <= '0';
        wait for 50 us;
        s_qspi_cs <= '1';
        wait for 100 us;

        s_qspi_cs <= '0';
        wait for 50 us;
        s_qspi_cs <= '1';
        wait for 100 us;

        enable <= false;
		wait;  -- don't do it again
	end process;

end architecture;

FPGA/VHDL/other_components/clear_led_logic/func.vcd
$date
  Mon Nov 03 09:21:30 2025
$end
$version
  GHDL v0
$end
$timescale
  1 ns
$end
$scope module standard $end
$upscope $end
$scope module textio $end
$upscope $end
$scope module std_logic_1164 $end
$upscope $end
$scope module numeric_std $end
$upscope $end
$scope module clear_led_logic_tb $end
$var reg 1 ! s_clock $end
$var reg 1 " s_reset $end
$var reg 1 # s_qspi_cs $end
$var reg 1 $ s_clear_led_pulse $end
$var reg 1 % s_clear_led_prohibit_fire $end
$var reg 1 & enable $end
$scope module dut $end
$var reg 1 ' clock_clk $end
$var reg 1 ( reset_reset $end
$var reg 1 ) qspi_cs $end
$var reg 1 * clear_led_pulse $end
$var reg 1 + clear_led_prohibit_fire $end
$var reg 8 , counter[7:0] $end
$var reg 6 - deadtime_counter[5:0] $end
$var reg 2 . qspi_cs_ff[1:0] $end
$var reg 6 / qspi_cs_done_ff[5:0] $end
$var reg 1 0 qspi_cs_done $end
$upscope $end
$upscope $end
$enddefinitions $end
#0
0!
0"
0#
0$
1%
1&
0'
0(
0)
0*
1+
b00000000 ,
b000000 -
b00 .
b000000 /
00
#41
1!
1'
#50
1"
1(
#82
0!
0'
#123
1!
1$
1'
1*
b00000001 ,
#164
0!
0'
#205
1!
0$
1'
0*
b00000010 ,
#246
0!
0'
#287
1!
1'
b00000011 ,
#328
0!
0'
#369
1!
1'
b00000100 ,
#410
0!
0'
#451
1!
1'
b00000101 ,
#492
0!
0'
#533
1!
1'
b00000110 ,
#574
0!
0'
#615
1!
1'
b00000111 ,
#656
0!
0'
#697
1!
1'
b00001000 ,
#738
0!
0'
#779
1!
1'
b00001001 ,
#820
0!
0'
#861
1!
1'
b00001010 ,
#902
0!
0'
#943
1!
1'
b00001011 ,
#984
0!
0'
#1025
1!
1'
b00001100 ,
#1066
0!
0'
#1107
1!
1'
b00001101 ,
#1148
0!
0'
#1189
1!
1'
b00001110 ,
#1230
0!
0'
#1271
1!
1'
b00001111 ,
#1312
0!
0'
#1353
1!
1'
b00010000 ,
#1394
0!
0'
#1435
1!
1'
b00010001 ,
#1476
0!
0'
#1517
1!
1'
b00010010 ,
#1558
0!
0'
#1599
1!
1'
b00010011 ,
#1640
0!
0'
#1681
1!
1'
b00010100 ,
#1722
0!
0'
#1763
1!
1'
b00010101 ,
#1804
0!
0'
#1845
1!
1'
b00010110 ,
#1886
0!
0'
#1927
1!
1'
b00010111 ,
#1968
0!
0'
#2009
1!
1'
b00011000 ,
#2050
0!
0'
#2091
1!
1'
b00011001 ,
#2132
0!
0'
#2173
1!
1'
b00011010 ,
#2214
0!
0'
#2255
1!
1'
b00011011 ,
#2296
0!
0'
#2337
1!
1'
b00011100 ,
#2378
0!
0'
#2419
1!
1'
b00011101 ,
#2460
0!
0'
#2501
1!
1'
b00011110 ,
#2542
0!
0'
#2583
1!
1'
b00011111 ,
#2624
0!
0'
#2665
1!
1'
b00100000 ,
#2706
0!
0'
#2747
1!
1'
b00100001 ,
#2788
0!
0'
#2829
1!
1'
b00100010 ,
#2870
0!
0'
#2911
1!
1'
b00100011 ,
#2952
0!
0'
#2993
1!
1'
b00100100 ,
#3034
0!
0'
#3075
1!
1'
b00100101 ,
#3116
0!
0'
#3157
1!
1'
b00100110 ,
#3198
0!
0'
#3239
1!
1'
b00100111 ,
#3280
0!
0'
#3321
1!
1'
b00101000 ,
#3362
0!
0'
#3403
1!
1'
b00101001 ,
#3444
0!
0'
#3485
1!
1'
b00101010 ,
#3526
0!
0'
#3567
1!
1'
b00101011 ,
#3608
0!
0'
#3649
1!
1'
b00101100 ,
#3690
0!
0'
#3731
1!
1'
b00101101 ,
#3772
0!
0'
#3813
1!
1'
b00101110 ,
#3854
0!
0'
#3895
1!
1'
b00101111 ,
#3936
0!
0'
#3977
1!
1'
b00110000 ,
#4018
0!
0'
#4059
1!
1'
b00110001 ,
#4100
0!
0'
#4141
1!
1'
b00110010 ,
#4182
0!
0'
#4223
1!
1'
b00110011 ,
#4264
0!
0'
#4305
1!
1'
b00110100 ,
#4346
0!
0'
#4387
1!
1'
b00110101 ,
#4428
0!
0'
#4469
1!
1'
b00110110 ,
#4510
0!
0'
#4551
1!
1'
b00110111 ,
#4592
0!
0'
#4633
1!
1'
b00111000 ,
#4674
0!
0'
#4715
1!
1'
b00111001 ,
#4756
0!
0'
#4797
1!
1'
b00111010 ,
#4838
0!
0'
#4879
1!
1'
b00111011 ,
#4920
0!
0'
#4961
1!
1'
b00111100 ,
#5002
0!
0'
#5043
1!
1'
b00111101 ,
#5084
0!
0'
#5125
1!
1'
b00111110 ,
#5166
0!
0'
#5207
1!
1'
b00111111 ,
#5248
0!
0'
#5289
1!
1'
b01000000 ,
#5330
0!
0'
#5371
1!
1'
b01000001 ,
#5412
0!
0'
#5453
1!
1'
b01000010 ,
#5494
0!
0'
#5535
1!
1'
b01000011 ,
#5576
0!
0'
#5617
1!
1'
b01000100 ,
#5658
0!
0'
#5699
1!
1'
b01000101 ,
#5740
0!
0'
#5781
1!
1'
b01000110 ,
#5822
0!
0'
#5863
1!
1'
b01000111 ,
#5904
0!
0'
#5945
1!
1'
b01001000 ,
#5986
0!
0'
#6027
1!
1'
b01001001 ,
#6068
0!
0'
#6109
1!
1'
b01001010 ,
#6150
0!
0'
#6191
1!
1'
b01001011 ,
#6232
0!
0'
#6273
1!
1'
b01001100 ,
#6314
0!
0'
#6355
1!
1'
b01001101 ,
#6396
0!
0'
#6437
1!
1'
b01001110 ,
#6478
0!
0'
#6519
1!
1'
b01001111 ,
#6560
0!
0'
#6601
1!
1'
b01010000 ,
#6642
0!
0'
#6683
1!
1'
b01010001 ,
#6724
0!
0'
#6765
1!
1'
b01010010 ,
#6806
0!
0'
#6847
1!
1'
b01010011 ,
#6888
0!
0'
#6929
1!
1'
b01010100 ,
#6970
0!
0'
#7011
1!
1'
b01010101 ,
#7052
0!
0'
#7093
1!
1'
b01010110 ,
#7134
0!
0'
#7175
1!
1'
b01010111 ,
#7216
0!
0'
#7257
1!
1'
b01011000 ,
#7298
0!
0'
#7339
1!
1'
b01011001 ,
#7380
0!
0'
#7421
1!
1'
b01011010 ,
#7462
0!
0'
#7503
1!
1'
b01011011 ,
#7544
0!
0'
#7585
1!
1'
b01011100 ,
#7626
0!
0'
#7667
1!
1'
b01011101 ,
#7708
0!
0'
#7749
1!
1'
b01011110 ,
#7790
0!
0'
#7831
1!
1'
b01011111 ,
#7872
0!
0'
#7913
1!
1'
b01100000 ,
#7954
0!
0'
#7995
1!
1'
b01100001 ,
#8036
0!
0'
#8077
1!
1'
b01100010 ,
#8118
0!
0'
#8159
1!
1'
b01100011 ,
#8200
0!
0'
#8241
1!
1'
b01100100 ,
#8282
0!
0'
#8323
1!
1'
b01100101 ,
#8364
0!
0'
#8405
1!
1'
b01100110 ,
#8446
0!
0'
#8487
1!
1'
b01100111 ,
#8528
0!
0'
#8569
1!
1'
b01101000 ,
#8610
0!
0'
#8651
1!
1'
b01101001 ,
#8692
0!
0'
#8733
1!
1'
b01101010 ,
#8774
0!
0'
#8815
1!
1'
b01101011 ,
#8856
0!
0'
#8897
1!
1'
b01101100 ,
#8938
0!
0'
#8979
1!
1'
b01101101 ,
#9020
0!
0'
#9061
1!
1'
b01101110 ,
#9102
0!
0'
#9143
1!
1'
b01101111 ,
#9184
0!
0'
#9225
1!
1'
b01110000 ,
#9266
0!
0'
#9307
1!
1'
b01110001 ,
#9348
0!
0'
#9389
1!
1'
b01110010 ,
#9430
0!
0'
#9471
1!
1'
b01110011 ,
#9512
0!
0'
#9553
1!
1'
b01110100 ,
#9594
0!
0'
#9635
1!
1'
b01110101 ,
#9676
0!
0'
#9717
1!
1'
b01110110 ,
#9758
0!
0'
#9799
1!
1'
b01110111 ,
#9840
0!
0'
#9881
1!
1'
b01111000 ,
#9922
0!
0'
#9963
1!
1'
b01111001 ,
#10004
0!
0'
#10045
1!
1'
b01111010 ,
#10086
0!
0'
#10127
1!
1'
b01111011 ,
#10168
0!
0'
#10209
1!
1'
b01111100 ,
#10250
0!
0'
#10291
1!
1'
b01111101 ,
#10332
0!
0'
#10373
1!
1'
b01111110 ,
#10414
0!
0'
#10455
1!
1'
b01111111 ,
#10496
0!
0'
#10537
1!
1'
b10000000 ,
#10578
0!
0'
#10619
1!
1'
b10000001 ,
#10660
0!
0'
#10701
1!
1'
b10000010 ,
#10742
0!
0'
#10783
1!
1'
b10000011 ,
#10824
0!
0'
#10865
1!
1'
b10000100 ,
#10906
0!
0'
#10947
1!
1'
b10000101 ,
#10988
0!
0'
#11029
1!
1'
b10000110 ,
#11070
0!
0'
#11111
1!
1'
b10000111 ,
#11152
0!
0'
#11193
1!
1'
b10001000 ,
#11234
0!
0'
#11275
1!
1'
b10001001 ,
#11316
0!
0'
#11357
1!
1'
b10001010 ,
#11398
0!
0'
#11439
1!
1'
b10001011 ,
#11480
0!
0'
#11521
1!
1'
b10001100 ,
#11562
0!
0'
#11603
1!
1'
b10001101 ,
#11644
0!
0'
#11685
1!
1'
b10001110 ,
#11726
0!
0'
#11767
1!
1'
b10001111 ,
#11808
0!
0'
#11849
1!
1'
b10010000 ,
#11890
0!
0'
#11931
1!
1'
b10010001 ,
#11972
0!
0'
#12013
1!
1'
b10010010 ,
#12054
0!
0'
#12095
1!
1'
b10010011 ,
#12136
0!
0'
#12177
1!
1'
b10010100 ,
#12218
0!
0'
#12259
1!
1'
b10010101 ,
#12300
0!
0'
#12341
1!
1'
b10010110 ,
#12382
0!
0'
#12423
1!
1'
b10010111 ,
#12464
0!
0'
#12505
1!
1'
b10011000 ,
#12546
0!
0'
#12587
1!
1'
b10011001 ,
#12628
0!
0'
#12669
1!
1'
b10011010 ,
#12710
0!
0'
#12751
1!
1'
b10011011 ,
#12792
0!
0'
#12833
1!
1'
b10011100 ,
#12874
0!
0'
#12915
1!
1'
b10011101 ,
#12956
0!
0'
#12997
1!
1'
b10011110 ,
#13038
0!
0'
#13079
1!
1'
b10011111 ,
#13120
0!
0'
#13161
1!
1'
b10100000 ,
#13202
0!
0'
#13243
1!
1'
b10100001 ,
#13284
0!
0'
#13325
1!
1'
b10100010 ,
#13366
0!
0'
#13407
1!
1'
b10100011 ,
#13448
0!
0'
#13489
1!
1'
b10100100 ,
#13530
0!
0'
#13571
1!
1'
b10100101 ,
#13612
0!
0'
#13653
1!
1'
b10100110 ,
#13694
0!
0'
#13735
1!
1'
b10100111 ,
#13776
0!
0'
#13817
1!
1'
b10101000 ,
#13858
0!
0'
#13899
1!
1'
b10101001 ,
#13940
0!
0'
#13981
1!
1'
b10101010 ,
#14022
0!
0'
#14063
1!
1'
b10101011 ,
#14104
0!
0'
#14145
1!
1'
b10101100 ,
#14186
0!
0'
#14227
1!
1'
b10101101 ,
#14268
0!
0'
#14309
1!
1'
b10101110 ,
#14350
0!
0'
#14391
1!
1'
b10101111 ,
#14432
0!
0'
#14473
1!
1'
b10110000 ,
#14514
0!
0'
#14555
1!
1'
b10110001 ,
#14596
0!
0'
#14637
1!
1'
b10110010 ,
#14678
0!
0'
#14719
1!
1'
b10110011 ,
#14760
0!
0'
#14801
1!
1'
b10110100 ,
#14842
0!
0'
#14883
1!
1'
b10110101 ,
#14924
0!
0'
#14965
1!
1'
b10110110 ,
#15006
0!
0'
#15047
1!
1'
b10110111 ,
#15088
0!
0'
#15129
1!
1'
b10111000 ,
#15170
0!
0'
#15211
1!
1'
b10111001 ,
#15252
0!
0'
#15293
1!
1'
b10111010 ,
#15334
0!
0'
#15375
1!
1'
b10111011 ,
#15416
0!
0'
#15457
1!
1'
b10111100 ,
#15498
0!
0'
#15539
1!
1'
b10111101 ,
#15580
0!
0'
#15621
1!
1'
b10111110 ,
#15662
0!
0'
#15703
1!
1'
b10111111 ,
#15744
0!
0'
#15785
1!
1'
b11000000 ,
#15826
0!
0'
#15867
1!
1'
b11000001 ,
#15908
0!
0'
#15949
1!
1'
b11000010 ,
#15990
0!
0'
#16031
1!
1'
b11000011 ,
#16072
0!
0'
#16113
1!
1'
b11000100 ,
#16154
0!
0'
#16195
1!
1'
b11000101 ,
#16236
0!
0'
#16277
1!
1'
b11000110 ,
#16318
0!
0'
#16359
1!
1'
b11000111 ,
#16400
0!
0'
#16441
1!
1'
b11001000 ,
#16482
0!
0'
#16523
1!
1'
b11001001 ,
#16564
0!
0'
#16605
1!
1'
b11001010 ,
#16646
0!
0'
#16687
1!
1'
b11001011 ,
#16728
0!
0'
#16769
1!
1'
b11001100 ,
#16810
0!
0'
#16851
1!
1'
b11001101 ,
#16892
0!
0'
#16933
1!
1'
b11001110 ,
#16974
0!
0'
#17015
1!
1'
b11001111 ,
#17056
0!
0'
#17097
1!
1'
b11010000 ,
#17138
0!
0'
#17179
1!
1'
b11010001 ,
#17220
0!
0'
#17261
1!
1'
b11010010 ,
#17302
0!
0'
#17343
1!
1'
b11010011 ,
#17384
0!
0'
#17425
1!
1'
b11010100 ,
#17466
0!
0'
#17507
1!
1'
b11010101 ,
#17548
0!
0'
#17589
1!
1'
b11010110 ,
#17630
0!
0'
#17671
1!
1'
b11010111 ,
#17712
0!
0'
#17753
1!
1'
b11011000 ,
#17794
0!
0'
#17835
1!
1'
b11011001 ,
#17876
0!
0'
#17917
1!
1'
b11011010 ,
#17958
0!
0'
#17999
1!
1'
b11011011 ,
#18040
0!
0'
#18081
1!
1'
b11011100 ,
#18122
0!
0'
#18163
1!
1'
b11011101 ,
#18204
0!
0'
#18245
1!
1'
b11011110 ,
#18286
0!
0'
#18327
1!
1'
b11011111 ,
#18368
0!
0'
#18409
1!
1'
b11100000 ,
#18450
0!
0'
#18491
1!
1'
b11100001 ,
#18532
0!
0'
#18573
1!
1'
b11100010 ,
#18614
0!
0'
#18655
1!
1'
b11100011 ,
#18696
0!
0'
#18737
1!
1'
b11100100 ,
#18778
0!
0'
#18819
1!
1'
b11100101 ,
#18860
0!
0'
#18901
1!
1'
b11100110 ,
#18942
0!
0'
#18983
1!
1'
b11100111 ,
#19024
0!
0'
#19065
1!
1'
b11101000 ,
#19106
0!
0'
#19147
1!
1'
b11101001 ,
#19188
0!
0'
#19229
1!
1'
b11101010 ,
#19270
0!
0'
#19311
1!
1'
b11101011 ,
#19352
0!
0'
#19393
1!
1'
b11101100 ,
#19434
0!
0'
#19475
1!
1'
b11101101 ,
#19516
0!
0'
#19557
1!
1'
b11101110 ,
#19598
0!
0'
#19639
1!
1'
b11101111 ,
#19680
0!
0'
#19721
1!
1'
b11110000 ,
#19762
0!
0'
#19803
1!
1'
b11110001 ,
#19844
0!
0'
#19885
1!
1'
b11110010 ,
#19926
0!
0'
#19967
1!
1'
b11110011 ,
#20008
0!
0'
#20049
1!
1'
b11110100 ,
#20090
0!
0'
#20131
1!
1'
b11110101 ,
#20172
0!
0'
#20213
1!
1'
b11110110 ,
#20254
0!
0'
#20295
1!
1'
b11110111 ,
#20336
0!
0'
#20377
1!
1'
b11111000 ,
#20418
0!
0'
#20459
1!
1'
b11111001 ,
#20500
0!
0'
#20541
1!
1'
b11111010 ,
#20582
0!
0'
#20623
1!
1'
b11111011 ,
#20664
0!
0'
#20705
1!
1'
b11111100 ,
#20746
0!
0'
#20787
1!
1'
b11111101 ,
#20828
0!
0'
#20869
1!
1'
b11111110 ,
#20910
0!
0'
#20951
1!
1'
b11111111 ,
#20992
0!
0'
#21033
1!
1'
b00000000 ,
#21074
0!
0'
#21115
1!
1$
1'
1*
b00000001 ,
#21156
0!
0'
#21197
1!
0$
1'
0*
b00000010 ,
#21238
0!
0'
#21279
1!
1'
b00000011 ,
#21320
0!
0'
#21361
1!
1'
b00000100 ,
#21402
0!
0'
#21443
1!
1'
b00000101 ,
#21484
0!
0'
#21525
1!
1'
b00000110 ,
#21566
0!
0'
#21607
1!
1'
b00000111 ,
#21648
0!
0'
#21689
1!
1'
b00001000 ,
#21730
0!
0'
#21771
1!
1'
b00001001 ,
#21812
0!
0'
#21853
1!
1'
b00001010 ,
#21894
0!
0'
#21935
1!
1'
b00001011 ,
#21976
0!
0'
#22017
1!
1'
b00001100 ,
#22058
0!
0'
#22099
1!
1'
b00001101 ,
#22140
0!
0'
#22181
1!
1'
b00001110 ,
#22222
0!
0'
#22263
1!
1'
b00001111 ,
#22304
0!
0'
#22345
1!
1'
b00010000 ,
#22386
0!
0'
#22427
1!
1'
b00010001 ,
#22468
0!
0'
#22509
1!
1'
b00010010 ,
#22550
0!
0'
#22591
1!
1'
b00010011 ,
#22632
0!
0'
#22673
1!
1'
b00010100 ,
#22714
0!
0'
#22755
1!
1'
b00010101 ,
#22796
0!
0'
#22837
1!
1'
b00010110 ,
#22878
0!
0'
#22919
1!
1'
b00010111 ,
#22960
0!
0'
#23001
1!
1'
b00011000 ,
#23042
0!
0'
#23083
1!
1'
b00011001 ,
#23124
0!
0'
#23165
1!
1'
b00011010 ,
#23206
0!
0'
#23247
1!
1'
b00011011 ,
#23288
0!
0'
#23329
1!
1'
b00011100 ,
#23370
0!
0'
#23411
1!
1'
b00011101 ,
#23452
0!
0'
#23493
1!
1'
b00011110 ,
#23534
0!
0'
#23575
1!
1'
b00011111 ,
#23616
0!
0'
#23657
1!
1'
b00100000 ,
#23698
0!
0'
#23739
1!
1'
b00100001 ,
#23780
0!
0'
#23821
1!
1'
b00100010 ,
#23862
0!
0'
#23903
1!
1'
b00100011 ,
#23944
0!
0'
#23985
1!
1'
b00100100 ,
#24026
0!
0'
#24067
1!
1'
b00100101 ,
#24108
0!
0'
#24149
1!
1'
b00100110 ,
#24190
0!
0'
#24231
1!
1'
b00100111 ,
#24272
0!
0'
#24313
1!
1'
b00101000 ,
#24354
0!
0'
#24395
1!
1'
b00101001 ,
#24436
0!
0'
#24477
1!
1'
b00101010 ,
#24518
0!
0'
#24559
1!
1'
b00101011 ,
#24600
0!
0'
#24641
1!
1'
b00101100 ,
#24682
0!
0'
#24723
1!
1'
b00101101 ,
#24764
0!
0'
#24805
1!
1'
b00101110 ,
#24846
0!
0'
#24887
1!
1'
b00101111 ,
#24928
0!
0'
#24969
1!
1'
b00110000 ,
#25010
0!
0'
#25051
1!
1'
b00110001 ,
#25092
0!
0'
#25133
1!
1'
b00110010 ,
#25174
0!
0'
#25215
1!
1'
b00110011 ,
#25256
0!
0'
#25297
1!
1'
b00110100 ,
#25338
0!
0'
#25379
1!
1'
b00110101 ,
#25420
0!
0'
#25461
1!
1'
b00110110 ,
#25502
0!
0'
#25543
1!
1'
b00110111 ,
#25584
0!
0'
#25625
1!
1'
b00111000 ,
#25666
0!
0'
#25707
1!
1'
b00111001 ,
#25748
0!
0'
#25789
1!
1'
b00111010 ,
#25830
0!
0'
#25871
1!
1'
b00111011 ,
#25912
0!
0'
#25953
1!
1'
b00111100 ,
#25994
0!
0'
#26035
1!
1'
b00111101 ,
#26076
0!
0'
#26117
1!
1'
b00111110 ,
#26158
0!
0'
#26199
1!
1'
b00111111 ,
#26240
0!
0'
#26281
1!
1'
b01000000 ,
#26322
0!
0'
#26363
1!
1'
b01000001 ,
#26404
0!
0'
#26445
1!
1'
b01000010 ,
#26486
0!
0'
#26527
1!
1'
b01000011 ,
#26568
0!
0'
#26609
1!
1'
b01000100 ,
#26650
0!
0'
#26691
1!
1'
b01000101 ,
#26732
0!
0'
#26773
1!
1'
b01000110 ,
#26814
0!
0'
#26855
1!
1'
b01000111 ,
#26896
0!
0'
#26937
1!
1'
b01001000 ,
#26978
0!
0'
#27019
1!
1'
b01001001 ,
#27060
0!
0'
#27101
1!
1'
b01001010 ,
#27142
0!
0'
#27183
1!
1'
b01001011 ,
#27224
0!
0'
#27265
1!
1'
b01001100 ,
#27306
0!
0'
#27347
1!
1'
b01001101 ,
#27388
0!
0'
#27429
1!
1'
b01001110 ,
#27470
0!
0'
#27511
1!
1'
b01001111 ,
#27552
0!
0'
#27593
1!
1'
b01010000 ,
#27634
0!
0'
#27675
1!
1'
b01010001 ,
#27716
0!
0'
#27757
1!
1'
b01010010 ,
#27798
0!
0'
#27839
1!
1'
b01010011 ,
#27880
0!
0'
#27921
1!
1'
b01010100 ,
#27962
0!
0'
#28003
1!
1'
b01010101 ,
#28044
0!
0'
#28085
1!
1'
b01010110 ,
#28126
0!
0'
#28167
1!
1'
b01010111 ,
#28208
0!
0'
#28249
1!
1'
b01011000 ,
#28290
0!
0'
#28331
1!
1'
b01011001 ,
#28372
0!
0'
#28413
1!
1'
b01011010 ,
#28454
0!
0'
#28495
1!
1'
b01011011 ,
#28536
0!
0'
#28577
1!
1'
b01011100 ,
#28618
0!
0'
#28659
1!
1'
b01011101 ,
#28700
0!
0'
#28741
1!
1'
b01011110 ,
#28782
0!
0'
#28823
1!
1'
b01011111 ,
#28864
0!
0'
#28905
1!
1'
b01100000 ,
#28946
0!
0'
#28987
1!
1'
b01100001 ,
#29028
0!
0'
#29069
1!
1'
b01100010 ,
#29110
0!
0'
#29151
1!
1'
b01100011 ,
#29192
0!
0'
#29233
1!
1'
b01100100 ,
#29274
0!
0'
#29315
1!
1'
b01100101 ,
#29356
0!
0'
#29397
1!
1'
b01100110 ,
#29438
0!
0'
#29479
1!
1'
b01100111 ,
#29520
0!
0'
#29561
1!
1'
b01101000 ,
#29602
0!
0'
#29643
1!
1'
b01101001 ,
#29684
0!
0'
#29725
1!
1'
b01101010 ,
#29766
0!
0'
#29807
1!
1'
b01101011 ,
#29848
0!
0'
#29889
1!
1'
b01101100 ,
#29930
0!
0'
#29971
1!
1'
b01101101 ,
#30012
0!
0'
#30053
1!
1'
b01101110 ,
#30094
0!
0'
#30135
1!
1'
b01101111 ,
#30176
0!
0'
#30217
1!
1'
b01110000 ,
#30258
0!
0'
#30299
1!
1'
b01110001 ,
#30340
0!
0'
#30381
1!
1'
b01110010 ,
#30422
0!
0'
#30463
1!
1'
b01110011 ,
#30504
0!
0'
#30545
1!
1'
b01110100 ,
#30586
0!
0'
#30627
1!
1'
b01110101 ,
#30668
0!
0'
#30709
1!
1'
b01110110 ,
#30750
0!
0'
#30791
1!
1'
b01110111 ,
#30832
0!
0'
#30873
1!
1'
b01111000 ,
#30914
0!
0'
#30955
1!
1'
b01111001 ,
#30996
0!
0'
#31037
1!
1'
b01111010 ,
#31078
0!
0'
#31119
1!
1'
b01111011 ,
#31160
0!
0'
#31201
1!
1'
b01111100 ,
#31242
0!
0'
#31283
1!
1'
b01111101 ,
#31324
0!
0'
#31365
1!
1'
b01111110 ,
#31406
0!
0'
#31447
1!
1'
b01111111 ,
#31488
0!
0'
#31529
1!
1'
b10000000 ,
#31570
0!
0'
#31611
1!
1'
b10000001 ,
#31652
0!
0'
#31693
1!
1'
b10000010 ,
#31734
0!
0'
#31775
1!
1'
b10000011 ,
#31816
0!
0'
#31857
1!
1'
b10000100 ,
#31898
0!
0'
#31939
1!
1'
b10000101 ,
#31980
0!
0'
#32021
1!
1'
b10000110 ,
#32062
0!
0'
#32103
1!
1'
b10000111 ,
#32144
0!
0'
#32185
1!
1'
b10001000 ,
#32226
0!
0'
#32267
1!
1'
b10001001 ,
#32308
0!
0'
#32349
1!
1'
b10001010 ,
#32390
0!
0'
#32431
1!
1'
b10001011 ,
#32472
0!
0'
#32513
1!
1'
b10001100 ,
#32554
0!
0'
#32595
1!
1'
b10001101 ,
#32636
0!
0'
#32677
1!
1'
b10001110 ,
#32718
0!
0'
#32759
1!
1'
b10001111 ,
#32800
0!
0'
#32841
1!
1'
b10010000 ,
#32882
0!
0'
#32923
1!
1'
b10010001 ,
#32964
0!
0'
#33005
1!
1'
b10010010 ,
#33046
0!
0'
#33087
1!
1'
b10010011 ,
#33128
0!
0'
#33169
1!
1'
b10010100 ,
#33210
0!
0'
#33251
1!
1'
b10010101 ,
#33292
0!
0'
#33333
1!
1'
b10010110 ,
#33374
0!
0'
#33415
1!
1'
b10010111 ,
#33456
0!
0'
#33497
1!
1'
b10011000 ,
#33538
0!
0'
#33579
1!
1'
b10011001 ,
#33620
0!
0'
#33661
1!
1'
b10011010 ,
#33702
0!
0'
#33743
1!
1'
b10011011 ,
#33784
0!
0'
#33825
1!
1'
b10011100 ,
#33866
0!
0'
#33907
1!
1'
b10011101 ,
#33948
0!
0'
#33989
1!
1'
b10011110 ,
#34030
0!
0'
#34071
1!
1'
b10011111 ,
#34112
0!
0'
#34153
1!
1'
b10100000 ,
#34194
0!
0'
#34235
1!
1'
b10100001 ,
#34276
0!
0'
#34317
1!
1'
b10100010 ,
#34358
0!
0'
#34399
1!
1'
b10100011 ,
#34440
0!
0'
#34481
1!
1'
b10100100 ,
#34522
0!
0'
#34563
1!
1'
b10100101 ,
#34604
0!
0'
#34645
1!
1'
b10100110 ,
#34686
0!
0'
#34727
1!
1'
b10100111 ,
